scripts_of_tribute/__init__.py
scripts_of_tribute/base_ai.py
scripts_of_tribute/board.py
scripts_of_tribute/enums.py
scripts_of_tribute/game.py
scripts_of_tribute/move.py
scripts_of_tribute/runner.py
scripts_of_tribute/server.py
scripts_of_tribute/protos/__init__.py
scripts_of_tribute/protos/basics_pb2.py
scripts_of_tribute/protos/basics_pb2_grpc.py
scripts_of_tribute/protos/enums_pb2.py
scripts_of_tribute/protos/enums_pb2_grpc.py
scripts_of_tribute/protos/main_pb2.py
scripts_of_tribute/protos/main_pb2_grpc.py
scripts_of_tribute-1.1.0.dist-info/licenses/LICENSE
scripts_of_tribute-1.1.0.dist-info/METADATA
scripts_of_tribute-1.1.0.dist-info/WHEEL
scripts_of_tribute-1.1.0.dist-info/top_level.txt
scripts_of_tribute-1.1.0.dist-info/RECORD
