Metadata-Version: 2.4
Name: scripts-of-tribute
Version: 1.1.0
Summary: Library wrapper to create bots for Scripts of Tribute AI programming game. It runs gRPC client-servers instances and connect with main engine made in C#
Author-email: Ematerasu <tot.thesis.project@gmail.com>
License: MIT License
Project-URL: Homepage, https://github.com/Ematerasu/ScriptsOfTribute-Python
Classifier: Programming Language :: Python :: 3
Classifier: License :: OSI Approved :: MIT License
Classifier: Operating System :: OS Independent
Requires-Python: >=3.10
License-File: LICENSE
Requires-Dist: grpcio>=1.68.0
Requires-Dist: grpcio-tools>=1.68.0
Requires-Dist: protobuf>=5.29.0
Requires-Dist: requests>=2.0
Dynamic: license-file
